splinecy.cpython-313-x86_64-linux-gnu.so
multispline/spline.py
multispline/__init__.py
multispline/tests/test_cubic.py
multispline/tests/test_tricubic.py
multispline/tests/__init__.py
multispline/tests/test_bicubic.py
multispline-0.8.5.dist-info/WHEEL
multispline-0.8.5.dist-info/RECORD
multispline-0.8.5.dist-info/METADATA
multispline-0.8.5.dist-info/licenses/LICENSE
