Metadata-Version: 2.1
Name: multispline
Version: 0.8.5
Summary: Cubic splines in multiple dimensions
Author: Zach Nasipak
Classifier: Programming Language :: Python :: 3
Classifier: License :: OSI Approved :: MIT License
Classifier: Natural Language :: English
Classifier: Programming Language :: C++
Classifier: Programming Language :: Cython
Requires-Python: >=3.7
Requires-Dist: numpy
